README.md
setup.cfg
setup.py
qrtt/__init__.py
qrtt.egg-info/PKG-INFO
qrtt.egg-info/SOURCES.txt
qrtt.egg-info/dependency_links.txt
qrtt.egg-info/requires.txt
qrtt.egg-info/top_level.txt
qrtt/data/__init__.py
qrtt/data/alpha_vantage.py
qrtt/data/stock_data.py
qrtt/technical/__init__.py
qrtt/technical/boll.py
qrtt/technical/cmci.py
qrtt/technical/ema.py
qrtt/technical/ma.py
qrtt/technical/macd.py
qrtt/technical/roc.py
qrtt/technical/rsi.py
qrtt/technical/sma.py
qrtt/technical/wlpr.py