Metadata-Version: 1.1
Name: qrtt
Version: 0.0.2
Summary: Quantitative research and trading tools.
Home-page: https://qrtt.org
Author: Leopold W.
Author-email: lsw@lwco.com
License: UNKNOWN
Download-URL: https://github.com/leopoldsw/qrtt/archive/v0.0.2.tar.gz
Platform: UNKNOWN
